openet_client/__init__.py
openet_client/cache.py
openet_client/client.py
openet_client/exceptions.py
openet_client/geodatabase.py
openet_client/raster.py
openet_client/timeseries.py
openet_client-2023.5.251.dist-info/LICENSE
openet_client-2023.5.251.dist-info/METADATA
openet_client-2023.5.251.dist-info/WHEEL
openet_client-2023.5.251.dist-info/top_level.txt
openet_client-2023.5.251.dist-info/RECORD
