Metadata-Version: 2.1
Name: openet-client
Version: 2023.5.251
Summary: Client for the OpenET web API with useful wrappers to support common workflows and needs with the API
Home-page: https://github.com/water3d/openet/
Author: nickrsan
Author-email: nsantos5@ucmerced.edu
License: MIT
Platform: UNKNOWN
Requires-Dist: requests
Requires-Dist: arrow
